MANIFEST.in
README.rst
setup.py
django_contenttype_tag.egg-info/PKG-INFO
django_contenttype_tag.egg-info/SOURCES.txt
django_contenttype_tag.egg-info/dependency_links.txt
django_contenttype_tag.egg-info/requires.txt
django_contenttype_tag.egg-info/top_level.txt
generic_ct_tag/__init__.py
generic_ct_tag/__init__.pyc
generic_ct_tag/models.py
generic_ct_tag/models.pyc
generic_ct_tag/tests.py
generic_ct_tag/tests.pyc
generic_ct_tag/templatetags/__init__.py
generic_ct_tag/templatetags/__init__.pyc
generic_ct_tag/templatetags/generic_ct.py
generic_ct_tag/templatetags/generic_ct.pyc